api/Logger.py
api/__init__.py
api/gpt.py
gpt4_api-0.2.4.dist-info/METADATA
gpt4_api-0.2.4.dist-info/WHEEL
gpt4_api-0.2.4.dist-info/top_level.txt
gpt4_api-0.2.4.dist-info/RECORD
